android_controller/__init__.py
android_controller/android_controller.py
android_controller-1.0.dist-info/LICENSE
android_controller-1.0.dist-info/METADATA
android_controller-1.0.dist-info/WHEEL
android_controller-1.0.dist-info/top_level.txt
android_controller-1.0.dist-info/RECORD
