Metadata-Version: 2.1
Name: android-controller
Version: 1.0
Summary: Module to control your android phone using code
Home-page: https://github.com/BennbuildVGC/android_controller
Author: Bennbuild
Author-email: bambrambam@gmail.com
License: MIT
Keywords: android automatization bot controller mobile phone wrapper
Platform: UNKNOWN
Classifier: License :: OSI Approved :: MIT License
Classifier: Programming Language :: Python :: 3
Classifier: Intended Audience :: Developers
Classifier: Operating System :: OS Independent
